dockerfile_recover/__init__.py
dockerfile_recover/__main__.py
dockerfile_recover/docker_api.py
dockerfile_recover/generator.py
dockerfile_recover/parser/__init__.py
dockerfile_recover/parser/exceptions.py
dockerfile_recover/parser/nop.py
dockerfile_recover/parser/parser.py
dockerfile_recover/parser/shell.py
dockerfile_recover-0.0.1a6.dist-info/entry_points.txt
dockerfile_recover-0.0.1a6.dist-info/LICENSE
dockerfile_recover-0.0.1a6.dist-info/WHEEL
dockerfile_recover-0.0.1a6.dist-info/METADATA
dockerfile_recover-0.0.1a6.dist-info/RECORD
