Metadata-Version: 2.1
Name: dockerfile-recover
Version: 0.0.1a6
Summary: dockerfile-recover is a tool to reconstruct Dockerfile by reverse engineering a docker image
Home-page: https://github.com/purificant/dockerfile-recover
License: MIT
Keywords: docker,dockerfile,recover,reverse,engineer
Requires-Python: >=3.9,<4.0
Classifier: Development Status :: 3 - Alpha
Classifier: License :: OSI Approved :: MIT License
Classifier: Operating System :: OS Independent
Classifier: Programming Language :: Python :: 3
Classifier: Programming Language :: Python :: 3.9
Classifier: Topic :: Utilities
Requires-Dist: click (>=8.0.1,<9.0.0)
Requires-Dist: docker (>=5.0.0,<6.0.0)
Requires-Dist: six (>=1.16.0,<2.0.0)
Project-URL: Documentation, https://github.com/purificant/dockerfile-recover
Project-URL: Repository, https://github.com/purificant/dockerfile-recover
